dhole/__init__.py
dhole/client.py
dhole-0.0.1.dist-info/LICENSE.txt
dhole-0.0.1.dist-info/METADATA
dhole-0.0.1.dist-info/WHEEL
dhole-0.0.1.dist-info/top_level.txt
dhole-0.0.1.dist-info/RECORD
