Metadata-Version: 2.1
Name: dhole
Version: 0.0.1
Summary: Currently just a test lib
Author: Berislav Paradžik
Author-email: <bparadzik.zg@gmail.com>
Keywords: python
Classifier: Development Status :: 1 - Planning
Classifier: Intended Audience :: Developers
Classifier: Programming Language :: Python :: 3
Classifier: Operating System :: Unix
Classifier: Operating System :: MacOS :: MacOS X
Classifier: Operating System :: Microsoft :: Windows
License-File: LICENSE.txt
